cho_util/__init__.py
cho_util/_version.py
cho_util/cam.py
cho_util/app/__init__.py
cho_util/app/config.py
cho_util/app/file_cache.py
cho_util/app/with_cli.py
cho_util/math/__init__.py
cho_util/math/common.py
cho_util/math/transform.py
cho_util/math/rotation/__init__.py
cho_util/math/rotation/_axis_angle.py
cho_util/math/rotation/_euler.py
cho_util/math/rotation/_matrix.py
cho_util/math/rotation/_quaternion.py
cho_util/math/rotation/axis_angle.py
cho_util/math/rotation/euler.py
cho_util/math/rotation/matrix.py
cho_util/math/rotation/quaternion.py
cho_util/viz/__init__.py
cho_util/viz/draw.py
cho_util/viz/gui.py
cho_util/viz/log.py
cho_util/viz/mpl.py
cho_util-0.2.1.data/scripts/pyhelp
cho_util-0.2.1.dist-info/LICENSE.txt
cho_util-0.2.1.dist-info/METADATA
cho_util-0.2.1.dist-info/WHEEL
cho_util-0.2.1.dist-info/top_level.txt
cho_util-0.2.1.dist-info/RECORD
